embassy.py
embassy-0.1.dist-info/WHEEL
embassy-0.1.dist-info/METADATA
embassy-0.1.dist-info/RECORD
