Metadata-Version: 2.1
Name: embassy
Version: 0.1
Summary: Python package for aligning embeddings and measuring alignment and stability errors.
Home-page: https://github.com/furkangursoy/embassy
License: UNKNOWN
Author: Furkan Gürsoy
Author-email: furkan.gursoy@boun.edu.tr
Classifier: License :: OSI Approved :: MIT License
